hamill/hamill.py
hamill-2.0.5.dist-info/METADATA
hamill-2.0.5.dist-info/WHEEL
hamill-2.0.5.dist-info/top_level.txt
hamill-2.0.5.dist-info/RECORD
